<annotation>
	<folder>Bilder</folder>
	<filename>resized_tools_on_granite_02.jpg</filename>
	<path>E:\Sciebo\Studium EIT BSc\8. Semester\Bachelorarbeit\Bilder\resized_tools_on_granite_02.jpg</path>
	<source>
		<database>Unknown</database>
	</source>
	<size>
		<width>640</width>
		<height>480</height>
		<depth>3</depth>
	</size>
	<segmented>0</segmented>
	<object>
		<name>Zange</name>
		<pose>Unspecified</pose>
		<truncated>0</truncated>
		<difficult>0</difficult>
		<bndbox>
			<xmin>156</xmin>
			<ymin>354</ymin>
			<xmax>385</xmax>
			<ymax>438</ymax>
		</bndbox>
	</object>
	<object>
		<name>Schraubendreher</name>
		<pose>Unspecified</pose>
		<truncated>0</truncated>
		<difficult>0</difficult>
		<bndbox>
			<xmin>64</xmin>
			<ymin>118</ymin>
			<xmax>138</xmax>
			<ymax>410</ymax>
		</bndbox>
	</object>
	<object>
		<name>Schraubendreher</name>
		<pose>Unspecified</pose>
		<truncated>0</truncated>
		<difficult>0</difficult>
		<bndbox>
			<xmin>402</xmin>
			<ymin>291</ymin>
			<xmax>616</xmax>
			<ymax>448</ymax>
		</bndbox>
	</object>
	<object>
		<name>Seitenschneider</name>
		<pose>Unspecified</pose>
		<truncated>0</truncated>
		<difficult>0</difficult>
		<bndbox>
			<xmin>441</xmin>
			<ymin>53</ymin>
			<xmax>567</xmax>
			<ymax>298</ymax>
		</bndbox>
	</object>
	<object>
		<name>Seitenschneider</name>
		<pose>Unspecified</pose>
		<truncated>0</truncated>
		<difficult>0</difficult>
		<bndbox>
			<xmin>117</xmin>
			<ymin>86</ymin>
			<xmax>352</xmax>
			<ymax>242</ymax>
		</bndbox>
	</object>
	<object>
		<name>Inbusschl端ssel</name>
		<pose>Unspecified</pose>
		<truncated>0</truncated>
		<difficult>0</difficult>
		<bndbox>
			<xmin>229</xmin>
			<ymin>228</ymin>
			<xmax>336</xmax>
			<ymax>321</ymax>
		</bndbox>
	</object>
	<object>
		<name>Inbusschl端ssel</name>
		<pose>Unspecified</pose>
		<truncated>0</truncated>
		<difficult>0</difficult>
		<bndbox>
			<xmin>335</xmin>
			<ymin>306</ymin>
			<xmax>466</xmax>
			<ymax>346</ymax>
		</bndbox>
	</object>
	<object>
		<name>Inbusschl端ssel</name>
		<pose>Unspecified</pose>
		<truncated>0</truncated>
		<difficult>0</difficult>
		<bndbox>
			<xmin>306</xmin>
			<ymin>91</ymin>
			<xmax>426</xmax>
			<ymax>221</ymax>
		</bndbox>
	</object>
	<object>
		<name>Inbusschl端ssel</name>
		<pose>Unspecified</pose>
		<truncated>0</truncated>
		<difficult>0</difficult>
		<bndbox>
			<xmin>361</xmin>
			<ymin>19</ymin>
			<xmax>467</xmax>
			<ymax>151</ymax>
		</bndbox>
	</object>
</annotation>
