<annotation>
	<folder>resized</folder>
	<filename>resized_PXL_20210930_144352089.jpg</filename>
	<path>/home/dennis/TensorFlow/workspace/training_demo/images/sweets_hd/train/resized/resized_PXL_20210930_144352089.jpg</path>
	<source>
		<database>Unknown</database>
	</source>
	<size>
		<width>1280</width>
		<height>960</height>
		<depth>3</depth>
	</size>
	<segmented>0</segmented>
	<object>
		<name>MAOAM</name>
		<pose>Unspecified</pose>
		<truncated>0</truncated>
		<difficult>0</difficult>
		<bndbox>
			<xmin>189</xmin>
			<ymin>662</ymin>
			<xmax>335</xmax>
			<ymax>858</ymax>
		</bndbox>
	</object>
	<object>
		<name>MAOAM</name>
		<pose>Unspecified</pose>
		<truncated>0</truncated>
		<difficult>0</difficult>
		<bndbox>
			<xmin>336</xmin>
			<ymin>240</ymin>
			<xmax>501</xmax>
			<ymax>436</ymax>
		</bndbox>
	</object>
	<object>
		<name>Snickers</name>
		<pose>Unspecified</pose>
		<truncated>0</truncated>
		<difficult>0</difficult>
		<bndbox>
			<xmin>342</xmin>
			<ymin>37</ymin>
			<xmax>659</xmax>
			<ymax>256</ymax>
		</bndbox>
	</object>
	<object>
		<name>Snickers</name>
		<pose>Unspecified</pose>
		<truncated>0</truncated>
		<difficult>0</difficult>
		<bndbox>
			<xmin>773</xmin>
			<ymin>198</ymin>
			<xmax>1068</xmax>
			<ymax>466</ymax>
		</bndbox>
	</object>
	<object>
		<name>Schokoriegel</name>
		<pose>Unspecified</pose>
		<truncated>0</truncated>
		<difficult>0</difficult>
		<bndbox>
			<xmin>579</xmin>
			<ymin>260</ymin>
			<xmax>817</xmax>
			<ymax>556</ymax>
		</bndbox>
	</object>
	<object>
		<name>Schokoriegel</name>
		<pose>Unspecified</pose>
		<truncated>0</truncated>
		<difficult>0</difficult>
		<bndbox>
			<xmin>92</xmin>
			<ymin>209</ymin>
			<xmax>247</xmax>
			<ymax>531</ymax>
		</bndbox>
	</object>
	<object>
		<name>MilkyWay</name>
		<pose>Unspecified</pose>
		<truncated>0</truncated>
		<difficult>0</difficult>
		<bndbox>
			<xmin>417</xmin>
			<ymin>571</ymin>
			<xmax>739</xmax>
			<ymax>767</ymax>
		</bndbox>
	</object>
	<object>
		<name>MilkyWay</name>
		<pose>Unspecified</pose>
		<truncated>0</truncated>
		<difficult>0</difficult>
		<bndbox>
			<xmin>867</xmin>
			<ymin>629</ymin>
			<xmax>1198</xmax>
			<ymax>808</ymax>
		</bndbox>
	</object>
</annotation>
